spaceway/__init__.py
spaceway/boost.py
spaceway/collection.py
spaceway/config.py
spaceway/debug.py
spaceway/hitbox.py
spaceway/icon.ico
spaceway/main.py
spaceway/mixins.py
spaceway/music.py
spaceway/updater.py
spaceway/assets/fonts/pixeboy.ttf
spaceway/assets/images/asteroid/blue_idle.bmp
spaceway/assets/images/asteroid/gray_idle.bmp
spaceway/assets/images/asteroid/red_idle.bmp
spaceway/assets/images/background/game.bmp
spaceway/assets/images/background/headpiece.bmp
spaceway/assets/images/background/updater.bmp
spaceway/assets/images/boosts/double_idle.bmp
spaceway/assets/images/boosts/double_small.bmp
spaceway/assets/images/boosts/mirror_idle.bmp
spaceway/assets/images/boosts/mirror_small.bmp
spaceway/assets/images/boosts/shield_activate.bmp
spaceway/assets/images/boosts/shield_idle.bmp
spaceway/assets/images/boosts/shield_small.bmp
spaceway/assets/images/boosts/time_idle.bmp
spaceway/assets/images/boosts/time_small.bmp
spaceway/assets/images/buttons/again.bmp
spaceway/assets/images/buttons/back.bmp
spaceway/assets/images/buttons/effects_0.bmp
spaceway/assets/images/buttons/effects_100.bmp
spaceway/assets/images/buttons/effects_25.bmp
spaceway/assets/images/buttons/effects_50.bmp
spaceway/assets/images/buttons/effects_75.bmp
spaceway/assets/images/buttons/full_screen_false.bmp
spaceway/assets/images/buttons/full_screen_true.bmp
spaceway/assets/images/buttons/lobby.bmp
spaceway/assets/images/buttons/music_0.bmp
spaceway/assets/images/buttons/music_100.bmp
spaceway/assets/images/buttons/music_25.bmp
spaceway/assets/images/buttons/music_50.bmp
spaceway/assets/images/buttons/music_75.bmp
spaceway/assets/images/buttons/play.bmp
spaceway/assets/images/buttons/resume.bmp
spaceway/assets/images/buttons/settings.bmp
spaceway/assets/images/buttons/table.bmp
spaceway/assets/images/buttons/updates_false.bmp
spaceway/assets/images/buttons/updates_true.bmp
spaceway/assets/images/heart/heart.bmp
spaceway/assets/images/inputs/nick_disable.bmp
spaceway-2.3.0.dist-info/LICENSE
spaceway-2.3.0.dist-info/METADATA
spaceway-2.3.0.dist-info/WHEEL
spaceway-2.3.0.dist-info/entry_points.txt
spaceway-2.3.0.dist-info/top_level.txt
spaceway-2.3.0.dist-info/RECORD
