Metadata-Version: 2.1
Name: spaceway
Version: 2.3.0
Summary: Space Way is arcade game about space, in which you must overcome the space path by flying around obstacles
Home-page: https://github.com/YariKartoshe4ka/Space-Way
Author: YariKartoshe4ka
Author-email: yaroslav.kikel.06@inbox.ru
Classifier: Programming Language :: Python :: 3
Classifier: Environment :: X11 Applications
Classifier: License :: OSI Approved :: GNU General Public License v3 (GPLv3)
Classifier: Topic :: Games/Entertainment :: Arcade
Classifier: Operating System :: OS Independent
Requires-Python: >=3.6.0
License-File: LICENSE
Requires-Dist: pygame (==2.1.2)
Requires-Dist: packaging (>=20.4)
Requires-Dist: requests (>=2.24.0)
Requires-Dist: platformdirs (>=2.1.0)
Requires-Dist: psutil (>=5.5.1)
